{
  "indexes": [
    {
      "collectionGroup": "progress",
      "queryScope": "COLLECTION",
      "fields": [
        { "fieldPath": "userId", "order": "ASCENDING" },
        { "fieldPath": "childId", "order": "ASCENDING" },
        { "fieldPath": "lessonId", "order": "ASCENDING" }
      ]
    },
    {
      "collectionGroup": "userUnlockedNpcs",
      "queryScope": "COLLECTION",
      "fields": [
        { "fieldPath": "userId", "order": "ASCENDING" },
        { "fieldPath": "npcId", "order": "ASCENDING" }
      ]
    }
  ],
  "fieldOverrides": []
}
